lcpcli/__init__.py
lcpcli/__main__.py
lcpcli/builder.py
lcpcli/check_files.py
lcpcli/cli.py
lcpcli/corpert.py
lcpcli/lcp_upload.py
lcpcli/lcpcli.py
lcpcli/utils.py
lcpcli/data/lcp_corpus_template.json
lcpcli/data/free_video_corpus/input/doc.conllu
lcpcli/data/free_video_corpus/input/meta.json
lcpcli/data/free_video_corpus/input/namedentity.csv
lcpcli/data/free_video_corpus/input/shot.csv
lcpcli/data/free_video_corpus/output/media/bunny.mp4
lcpcli/data/input/in.conllu
lcpcli/data/input/in.vert
lcpcli/data/input/in_tei_spoken.xml
lcpcli/parsers/__init__.py
lcpcli/parsers/_parser.py
lcpcli/parsers/conllu.py
lcpcli-0.2.8.dist-info/METADATA
lcpcli-0.2.8.dist-info/WHEEL
lcpcli-0.2.8.dist-info/entry_points.txt
lcpcli-0.2.8.dist-info/licenses/LICENSE.txt
lcpcli-0.2.8.dist-info/RECORD
