Metadata-Version: 2.4
Name: lcpcli
Version: 0.2.8
Summary: Helper for converting CONLLU files and uploading the corpus to LiRI Corpus Platform (LCP)
Project-URL: Homepage, https://github.com/liri-uzh/lcpcli/issues
Project-URL: Issues, https://github.com/liri-uzh/lcpcli/issues
Author-email: Danny McDonald <daniel.mcdonald@uzh.ch>, Igor Mustač <igor.mustac@uzh.ch>, Jeremy Zehr <jeremy.zehr@uzh.ch>, Jonathan Schaber <jeremy.schaber@uzh.ch>
License: MIT
License-File: LICENSE.txt
Keywords: CONLL,TEI,VERT,corpora,corpus,linguistics
Classifier: Development Status :: 4 - Beta
Classifier: Intended Audience :: Science/Research
Classifier: License :: OSI Approved :: MIT License
Classifier: Operating System :: OS Independent
Classifier: Programming Language :: Python :: 3
Requires-Python: >=3.10
Requires-Dist: diskcache>=5.6.3
Requires-Dist: jsonpickle>=3.0
Requires-Dist: jsonschema>=4.21
Requires-Dist: lupa>=1.13
Requires-Dist: lxml>=4.7.1
Requires-Dist: pandas>=2.2.2
Requires-Dist: py7zr>=0.20.5
Requires-Dist: requests>=2.30.0
Requires-Dist: tqdm>=4.65.0
Requires-Dist: types-requests>=2.30.0.0
Requires-Dist: types-tqdm>=4.65.0.1
Requires-Dist: xmltodict>=0.13
